LICENSE
LICENSE.txt
README.md
setup.cfg
setup.py
lab_test_class/__init__.py
lab_test_class/lab_test_class.py
lab_test_class.egg-info/PKG-INFO
lab_test_class.egg-info/SOURCES.txt
lab_test_class.egg-info/dependency_links.txt
lab_test_class.egg-info/requires.txt
lab_test_class.egg-info/top_level.txt