Metadata-Version: 2.1
Name: lab-test-class
Version: 0.1
Summary: processing lab tests
Author: Anis Kheffache
Author-email: Anis.kheffache@ugent.be,Aniskheffache@yahoo.fr
License: MIT
License-File: LICENSE
License-File: LICENSE.txt
